gtl2via/__init__.py
gtl2via/__main__.py
gtl2via/gtl2via.py
gtl2via-0.0.1.dist-info/LICENSE
gtl2via-0.0.1.dist-info/METADATA
gtl2via-0.0.1.dist-info/WHEEL
gtl2via-0.0.1.dist-info/entry_points.txt
gtl2via-0.0.1.dist-info/top_level.txt
gtl2via-0.0.1.dist-info/RECORD
