Metadata-Version: 2.1
Name: gtl2via
Version: 0.0.1
Summary: Converter from AWS SageMaker tto VIA
Home-page: https://github.com/jinzishuai/gtl2via
Author: Shi Jin
Author-email: jinzishuai@gmail.com
License: UNKNOWN
Platform: UNKNOWN
Classifier: Programming Language :: Python :: 3
Classifier: License :: OSI Approved :: MIT License
Classifier: Operating System :: OS Independent
Requires-Python: >=3.6
